onedoc/__init__.py
onedoc/html_builder.py
onedoc/merge.py
onedoc/onedoc.py
onedoc/split.py
client_onedoc-0.0.21.dist-info/METADATA
client_onedoc-0.0.21.dist-info/WHEEL
client_onedoc-0.0.21.dist-info/top_level.txt
client_onedoc-0.0.21.dist-info/RECORD
