Metadata-Version: 2.1
Name: client_onedoc
Version: 0.0.21
Summary: Onedoc SDK for Python
Author-email: Pierre Dorge <pierre.dorge@onedoclabs.com>, Titouan Launay <titouan.launay@onedoclabs.com>
Project-URL: Homepage, https://github.com/onedoclabs/onedoc
Project-URL: Issues, https://github.com/OnedocLabs/onedoc/issues
Classifier: Programming Language :: Python :: 3
Classifier: License :: OSI Approved :: MIT License
Classifier: Operating System :: OS Independent
Requires-Python: >=3.8
Requires-Dist: requests >=2.0
Requires-Dist: pikepdf >=8.13.0
